sonora/__init__.py
sonora/__version__.py
sonora/aio.py
sonora/asgi.py
sonora/client.py
sonora/echotest.py
sonora/protocol.py
sonora/wsgi.py
sonora-0.2.3.dist-info/LICENSE
sonora-0.2.3.dist-info/METADATA
sonora-0.2.3.dist-info/WHEEL
sonora-0.2.3.dist-info/RECORD
